mcscales_tools/__init__.py
mcscales_tools/checks.py
mcscales_tools/grouping.py
mcscales_tools/partition.py
mcscales_tools/theory_driven.py
mcscales_tools/vendor/__init__.py
mcscales_tools/vendor/compat.py
mcscales_tools/vendor/lhio.py
mcscales_tools-0.3.dist-info/entry_points.txt
mcscales_tools-0.3.dist-info/LICENSE
mcscales_tools-0.3.dist-info/WHEEL
mcscales_tools-0.3.dist-info/METADATA
mcscales_tools-0.3.dist-info/RECORD
