Metadata-Version: 2.1
Name: mcscales_tools
Version: 0.3
Summary: Tools for wroking with LHAPDF grids with MCScales (arxiv:2207.07616)
Author: Maria Ubiali, Cameron Voisey
Author-email: Zahari Kassabov <zk261@cam.ac.uk>
Requires-Python: >=3.7
Classifier: License :: OSI Approved :: GNU General Public License v3 or later (GPLv3+)
Requires-Dist: numpy ~= 1.21
Requires-Dist: pandas ~=1.2
Requires-Dist: ruamel.yaml ~=0.15
Project-URL: Home, https://github.com/Zaharid/mcscales_tools
